{
  "namespace": "random",
  "type_name": "random_i64_range",
  "description": "Random Signed Integer Within Range",
  "components": [
    {
      "namespace": "trigger",
      "type_name": "action"
    },
    {
      "namespace": "random",
      "type_name": "range"
    },
    {
      "namespace": "result",
      "type_name": "result_number"
    }
  ],
  "properties": [
  ],
  "extensions": [
    {
      "namespace": "metadata",
      "type_name": "dublin-core",
      "extension":{
        "title": "Random Signed Integer Within Range",
        "subject": "Random Signed Integer Within Range",
        "creator": "Hanack"
      }
    }
  ]
}
